realistic_username_generator/__init__.py
realistic_username_generator/main.py
realistic_username_generator-0.0.1.dist-info/METADATA
realistic_username_generator-0.0.1.dist-info/WHEEL
realistic_username_generator-0.0.1.dist-info/licenses/LICENSE
realistic_username_generator-0.0.1.dist-info/RECORD
