Metadata-Version: 2.3
Name: realistic_username_generator
Version: 0.0.1
Summary: A package for generating usernames
Project-URL: Homepage, https://github.com/lucid0z/realistic_username_generator
Project-URL: Issues, https://github.com/pypa/realistic_username_generator/issues
Author-email: Lucid <frantico1@proton.me>
License-File: LICENSE
Classifier: License :: OSI Approved :: MIT License
Classifier: Operating System :: OS Independent
Classifier: Programming Language :: Python :: 3
Requires-Python: >=3.8
